hpycc/__init__.py
hpycc/connection.py
hpycc/delete.py
hpycc/get.py
hpycc/run.py
hpycc/save.py
hpycc/spray.py
hpycc/utils/__init__.py
hpycc/utils/docker_tools.py
hpycc/utils/filechunker.py
hpycc/utils/parsers.py
tests/__init__.py
tests/test_with_server/__init__.py
tests/test_with_server/test_connection.py
tests/test_with_server/test_delete.py
tests/test_with_server/test_get.py
tests/test_with_server/test_run.py
tests/test_with_server/test_save.py
tests/test_with_server/test_spray.py
tests/test_without_server/__init__.py
tests/test_without_server/test_connection.py
tests/test_without_server/test_run.py
tests/test_without_server/test_utils/__init__.py
tests/test_without_server/test_utils/test_filechunker.py
tests/test_without_server/test_utils/test_parsers.py
hpycc-0.2.2.dist-info/LICENSE.txt
hpycc-0.2.2.dist-info/METADATA
hpycc-0.2.2.dist-info/WHEEL
hpycc-0.2.2.dist-info/top_level.txt
hpycc-0.2.2.dist-info/RECORD
