Metadata-Version: 2.1
Name: hpycc
Version: 0.2.2
Summary: Download THOR files, run ECL scripts and download their results.
Home-page: https://github.com/OdinProAgrica/hpycc
Author: Rob Mansfield
Author-email: rob.mansfield@proagrica.com
License: GNU GPLv3
Project-URL: Bug Reports, https://github.com/OdinProAgrica/hpycc/issues
Project-URL: Source, https://github.com/OdinProAgrica/hpycc
Project-URL: ReadTheDocs, http://hpycc.readthedocs.io
Keywords: HPCC ECL data access distributed ROXIE THOR
Platform: UNKNOWN
Classifier: Development Status :: 4 - Beta
Classifier: License :: OSI Approved :: GNU General Public License v3 or later (GPLv3+)
Classifier: Intended Audience :: Developers
Classifier: Intended Audience :: Information Technology
Classifier: Intended Audience :: Science/Research
Classifier: Natural Language :: English
Classifier: Programming Language :: Python :: 3
Classifier: Topic :: System :: Distributed Computing
Classifier: Topic :: Utilities
Requires-Dist: pandas
Requires-Dist: requests (>=2.18.4)
Requires-Dist: docker
Requires-Dist: numpy
Requires-Dist: passlib
Requires-Dist: simplejson (==3.16.0)
